pyradiora_classic/__init__.py
pyradiora_classic-0.0.6.dist-info/LICENSE.md
pyradiora_classic-0.0.6.dist-info/METADATA
pyradiora_classic-0.0.6.dist-info/WHEEL
pyradiora_classic-0.0.6.dist-info/top_level.txt
pyradiora_classic-0.0.6.dist-info/zip-safe
pyradiora_classic-0.0.6.dist-info/RECORD
